torchmerge/__init__.py
torchmerge/merge.py
torchmerge-0.1.16540980.dist-info/LICENSE
torchmerge-0.1.16540980.dist-info/METADATA
torchmerge-0.1.16540980.dist-info/WHEEL
torchmerge-0.1.16540980.dist-info/entry_points.txt
torchmerge-0.1.16540980.dist-info/top_level.txt
torchmerge-0.1.16540980.dist-info/RECORD
