Metadata-Version: 2.1
Name: torchmerge
Version: 0.1.16540980
Summary: torch
Home-page: UNKNOWN
Author: Kevin Noel
License: UNKNOWN
Keywords: torch
Platform: UNKNOWN
Classifier: Development Status :: 3 - Alpha
Classifier: Intended Audience :: End Users/Desktop
Classifier: Intended Audience :: Developers
Classifier: Intended Audience :: Science/Research
Classifier: License :: OSI Approved :: Apache Software License
Classifier: Programming Language :: Python :: 3
Classifier: Programming Language :: Python :: 3.6
Classifier: Topic :: Scientific/Engineering
Classifier: Topic :: Scientific/Engineering :: Artificial Intelligence
Classifier: Topic :: Software Development :: Libraries
Classifier: Topic :: Software Development :: Libraries :: Python Modules
Classifier: Topic :: Scientific/Engineering :: Information Analysis
Classifier: Environment :: Console
Classifier: Environment :: Web Environment
Classifier: Operating System :: POSIX
Classifier: Operating System :: MacOS :: MacOS X
Requires-Python: >=3.7.5
License-File: LICENSE
Requires-Dist: pyyaml
Requires-Dist: python-box
Requires-Dist: fire
Requires-Dist: utilmy
